KivyOnTop/__init__.py
KivyOnTop-1.4.dist-info/LICENSE
KivyOnTop-1.4.dist-info/METADATA
KivyOnTop-1.4.dist-info/WHEEL
KivyOnTop-1.4.dist-info/top_level.txt
KivyOnTop-1.4.dist-info/RECORD
