Metadata-Version: 2.1
Name: KivyOnTop
Version: 1.4
Summary: Makes Kivy windows stay on top of other windows.
Home-page: https://github.com/JakubBlaha/KivyOnTop
Author: Jakub Bláha
Author-email: jakub.blaha@example.com
License: UNKNOWN
Platform: UNKNOWN
Classifier: Programming Language :: Python :: 3
Classifier: Operating System :: Microsoft :: Windows
